confPy6/__init__.py
confPy6/controller/CObject.py
confPy6/controller/CSignal.py
confPy6/controller/ConfigNode.py
confPy6/controller/Field.py
confPy6/controller/SelectableList.py
confPy6/controller/VASInputFileParser.py
confPy6/controller/__init__.py
confPy6/controller/fields/FieldBool.py
confPy6/controller/fields/FieldFloat.py
confPy6/controller/fields/FieldInt.py
confPy6/controller/fields/FieldList.py
confPy6/controller/fields/FieldPath.py
confPy6/controller/fields/FieldSelectableList.py
confPy6/controller/fields/FieldString.py
confPy6/controller/fields/FieldTuple.py
confPy6/controller/fields/__init__.py
confPy6/view/ConfigEditor.py
confPy6/view/ConfigView.py
confPy6/view/FieldView.py
confPy6/view/__init__.py
confPy6/view/resources_rc.py
confPy6/view/fields/FieldViewBool.py
confPy6/view/fields/FieldViewFloat.py
confPy6/view/fields/FieldViewInt.py
confPy6/view/fields/FieldViewList.py
confPy6/view/fields/FieldViewPath.py
confPy6/view/fields/FieldViewSelectableList.py
confPy6/view/fields/FieldViewString.py
confPy6/view/fields/FieldViewTuple.py
confPy6-1.3.4.dist-info/LICENSE
confPy6-1.3.4.dist-info/METADATA
confPy6-1.3.4.dist-info/WHEEL
confPy6-1.3.4.dist-info/top_level.txt
confPy6-1.3.4.dist-info/RECORD
