Metadata-Version: 2.1
Name: confPy6
Version: 1.3.4
Summary: A configuration handler using pyside6
Author-email: Christoph Schmidt <cschmidt.fs@gmail.com>
Project-URL: Homepage, https://github.com/agentsmith29/confPy6
Classifier: Programming Language :: Python :: 3
Classifier: License :: OSI Approved :: GNU General Public License v3 (GPLv3)
Classifier: Operating System :: OS Independent
Requires-Python: >=3.7
License-File: LICENSE
Requires-Dist: pyside6
Requires-Dist: rich
Requires-Dist: pyyaml
